jaqs/__init__.py
jaqs/data/__init__.py
jaqs/data/align.py
jaqs/data/continue_contract.py
jaqs/data/dataservice.py
jaqs/data/dataview.py
jaqs/data/py_expression_eval.py
jaqs/data/basic/__init__.py
jaqs/data/basic/instrument.py
jaqs/data/basic/marketdata.py
jaqs/data/basic/order.py
jaqs/data/basic/position.py
jaqs/data/basic/trade.py
jaqs/data/dataapi/__init__.py
jaqs/data/dataapi/data_api.py
jaqs/data/dataapi/jrpc_py.py
jaqs/data/dataapi/utils.py
jaqs/research/__init__.py
jaqs/research/signaldigger/__init__.py
jaqs/research/signaldigger/digger.py
jaqs/research/signaldigger/performance.py
jaqs/research/signaldigger/plotting.py
jaqs/trade/__init__.py
jaqs/trade/backtest.py
jaqs/trade/common.py
jaqs/trade/livetrade.py
jaqs/trade/model.py
jaqs/trade/portfoliomanager.py
jaqs/trade/strategy.py
jaqs/trade/tradegateway.py
jaqs/trade/analyze/__init__.py
jaqs/trade/analyze/analyze.py
jaqs/trade/analyze/report.py
jaqs/trade/analyze/static/additional.css
jaqs/trade/analyze/static/report_template.html
jaqs/trade/analyze/static/test_template.html
jaqs/trade/analyze/static/bootstrap/css/bootstrap.min.css
jaqs/trade/analyze/static/bootstrap/js/bootstrap.min.js
jaqs/trade/analyze/static/bootstrap/js/jquery.slim.min.js
jaqs/trade/analyze/static/bootstrap/js/popper.min.js
jaqs/trade/analyze/static/bootstrap-toc/bootstrap-toc.min.css
jaqs/trade/analyze/static/bootstrap-toc/bootstrap-toc.min.js
jaqs/trade/event/__init__.py
jaqs/trade/event/engine.py
jaqs/trade/event/eventtype.py
jaqs/trade/tradeapi/__init__.py
jaqs/trade/tradeapi/jrpc_py.py
jaqs/trade/tradeapi/trade_api.py
jaqs/trade/tradeapi/utils.py
jaqs/util/__init__.py
jaqs/util/dtutil.py
jaqs/util/fileio.py
jaqs/util/numeric.py
jaqs/util/pdutil.py
jaqs/util/profile.py
jaqs/util/sequence.py
jaqs-0.6.14.dist-info/DESCRIPTION.rst
jaqs-0.6.14.dist-info/METADATA
jaqs-0.6.14.dist-info/RECORD
jaqs-0.6.14.dist-info/WHEEL
jaqs-0.6.14.dist-info/metadata.json
jaqs-0.6.14.dist-info/top_level.txt
