Metadata-Version: 2.0
Name: jaqs
Version: 0.6.14
Summary: Open source quantitative research&trading framework.
Home-page: https://github.com/quantOS-org/JAQS
Author: quantOS
Author-email: UNKNOWN
License: Apache 2.0
Keywords: quantiatitive trading research finance
Platform: UNKNOWN
Classifier: Development Status :: 4 - Beta
Classifier: Intended Audience :: Developers
Classifier: Intended Audience :: Education
Classifier: Intended Audience :: End Users/Desktop
Classifier: Intended Audience :: Financial and Insurance Industry
Classifier: Intended Audience :: Information Technology
Classifier: Intended Audience :: Science/Research
Classifier: License :: OSI Approved :: Apache Software License
Classifier: Natural Language :: Chinese (Simplified)
Classifier: Natural Language :: English
Classifier: Operating System :: Microsoft :: Windows
Classifier: Operating System :: Unix
Classifier: Programming Language :: Python :: 2.7
Classifier: Programming Language :: Python :: 3.6
Requires-Dist: future
Requires-Dist: Jinja2
Requires-Dist: msgpack-python
Requires-Dist: pandas (>=0.20.0)
Requires-Dist: pyzmq
Requires-Dist: python-snappy
Requires-Dist: seaborn
Requires-Dist: six
